freqtag/__init__.py
freqtag/_template.py
freqtag/_version.py
freqtag/tests/__init__.py
freqtag/tests/test_template.py
freq_tag-0.0.1.dist-info/LICENSE
freq_tag-0.0.1.dist-info/METADATA
freq_tag-0.0.1.dist-info/WHEEL
freq_tag-0.0.1.dist-info/top_level.txt
freq_tag-0.0.1.dist-info/RECORD
